framefile/__init__.py
framefile/_base.py
framefile/_constants.py
framefile/_deprecated.py
framefile-0.0.9.dist-info/LICENSE
framefile-0.0.9.dist-info/METADATA
framefile-0.0.9.dist-info/WHEEL
framefile-0.0.9.dist-info/top_level.txt
framefile-0.0.9.dist-info/RECORD
