Metadata-Version: 2.1
Name: framefile
Version: 0.0.9
Summary: Matching and parsing file names like IMG_####.JPG or IMG_%04d.JPG
Home-page: https://github.com/rtmigo/framefile_py
Author: Artёm IG
Author-email: ortemeo@gmail.com
License: MIT
Keywords: text,string,pattern,regex,parsing,integer,glob,hash,digit,number
Platform: UNKNOWN
Classifier: License :: OSI Approved :: MIT License
Classifier: Programming Language :: Python :: 3.7
Classifier: Programming Language :: Python :: 3.8
Classifier: Programming Language :: Python :: 3.9
Classifier: Programming Language :: Python :: 3.10
Classifier: Typing :: Typed
Classifier: Operating System :: POSIX
Classifier: Operating System :: Microsoft :: Windows
Requires-Python: >=3.7
License-File: LICENSE
